pylychee/__init__.py
pylychee/apps/__init__.py
pylychee/apps/feishu/__init__.py
pylychee/apps/feishu/messages.py
pylychee-0.0.4.dist-info/LICENSE
pylychee-0.0.4.dist-info/METADATA
pylychee-0.0.4.dist-info/WHEEL
pylychee-0.0.4.dist-info/top_level.txt
pylychee-0.0.4.dist-info/RECORD
